{
  "email": "E-post",
  "password": "Passord",
  "account": "Konto",
  "accounts": "Regnskap",
  "accountsDescription": "Bytt mellom kontoene du er logget på for øyeblikket.",
  "accountsInstructions": "Logg på en ekstra konto.",
  "addAccount": "Legg til konto",
  "addPasskey": "Legg til passnøkkel",
  "alreadyHaveAnAccount": "Har du allerede en konto?",
  "avatar": "Avatar",
  "avatarDescription": "Klikk på avataren for å laste opp en egendefinert avatar fra filene dine.",
  "avatarInstructions": "En avatar er valgfritt, men anbefales på det sterkeste.",
  "backupCodeRequired": "Sikkerhetskopieringskode er nødvendig",
  "backupCodes": "Sikkerhetskoder",
  "backupCodesDescription": "Lagre disse sikkerhetskopikodene på et sikkert sted. Du kan bruke dem til å få tilgang til kontoen din hvis du mister tofaktorautentiseringsmetoden.",
  "backupCodePlaceholder": "Sikkerhetskopieringskode",
  "backupCode": "Sikkerhetskopieringskode",
  "backupCodeAction": "Gjenopprett konto",
  "cancel": "Avbryt",
  "changePassword": "Endre passord",
  "changePasswordDescription": "Skriv inn ditt nåværende passord og et nytt passord.",
  "changePasswordInstructions": "Vennligst bruk minst 8 tegn.",
  "changePasswordSuccess": "Passordet ditt har blitt endret.",
  "confirmPassword": "Bekreft passord",
  "confirmPasswordPlaceholder": "Bekreft passord",
  "confirmPasswordRequired": "Bekreft passord er påkrevd",
  "continueWithAuthenticator": "Fortsett med Authenticator",
  "copiedToClipboard": "Kopieres til utklippstavlen",
  "copyToClipboard": "Kopier til utklippstavlen",
  "copyAllCodes": "Kopier alle koder",
  "continue": "Fortsett",
  "currentPassword": "Gjeldende passord",
  "currentPasswordPlaceholder": "Gjeldende passord",
  "currentSession": "Nåværende sesjon",
  "delete": "Slett",
  "deleteAvatar": "Slett avatar",
  "deleteAccount": "Slett konto",
  "deleteAccountDescription": "Fjern kontoen din og alt innholdet permanent. Denne handlingen kan ikke reverseres, så fortsett med forsiktighet.",
  "deleteAccountInstructions": "Vennligst bekreft slettingen av kontoen din. Denne handlingen kan ikke reverseres, så fortsett med forsiktighet.",
  "deleteAccountVerify": "Vennligst sjekk e-posten din for å bekrefte at kontoen din er slettet.",
  "deleteAccountSuccess": "Kontoen din er slettet.",
  "deleteAccountNotFresh": "Du må nylig ha logget inn for å slette kontoen din.",
  "disable": "Deaktiver",
  "disabledCredentialsDescription": "Velg en leverandør for å logge inn på kontoen din",
  "dontHaveAnAccount": "Har du ikke en konto?",
  "done": "Ferdig",
  "emailDescription": "Skriv inn e-postadressen du vil bruke til å logge på.",
  "emailInstructions": "Vennligst skriv inn en gyldig e-postadresse.",
  "emailInvalid": "E-postadressen er ugyldig",
  "emailIsTheSame": "E-post er det samme",
  "emailPlaceholder": "m@example.com",
  "emailRequired": "E-postadresse er påkrevd",
  "emailVerifyChange": "Vennligst sjekk e-posten din for å bekrefte endringen.",
  "emailVerification": "Sjekk e-posten din for bekreftelseskoblingen.",
  "enable": "Aktivere",
  "error": "Feil",
  "isInvalid": "er ugyldig",
  "isRequired": "er nødvendig",
  "isTheSame": "er den samme",
  "forgotAuthenticator": "Har du glemt autentiseringsenheten?",
  "forgotPassword": "Glemt passord",
  "forgotPasswordAction": "Send lenke for tilbakestilling",
  "forgotPasswordDescription": "Skriv inn e-postadressen din for å tilbakestille passordet ditt",
  "forgotPasswordEmail": "Sjekk e-posten din for lenke til tilbakestilling av passord.",
  "forgotPasswordLink": "Har du glemt passordet ditt?",
  "invalidTwoFactorCookie": "Ugyldig informasjonskapsel med to faktorer",
  "link": "Lenke",
  "magicLink": "Magisk lenke",
  "magicLinkAction": "Send magisk lenke",
  "magicLinkDescription": "Skriv inn e-postadressen din for å motta en magisk lenke",
  "magicLinkEmail": "Sjekk e-posten din for den magiske lenken",
  "emailOTP": "E-postkode",
  "emailOTPSendAction": "Send kode",
  "emailOTPVerifyAction": "Bekreft kode",
  "emailOTPDescription": "Skriv inn e-postadressen din for å motta en kode",
  "emailOTPVerificationSent": "Sjekk e-posten din for bekreftelseskoden.",
  "name": "Navn",
  "nameDescription": "Vennligst skriv inn ditt fulle navn eller et visningsnavn.",
  "nameInstructions": "Vennligst bruk maksimalt 32 tegn.",
  "namePlaceholder": "Navn",
  "newPassword": "Nytt passord",
  "newPasswordPlaceholder": "Nytt passord",
  "newPasswordRequired": "Nytt passord er påkrevd",
  "oneTimePassword": "Engangspassord",
  "orContinueWith": "Eller fortsett med",
  "passkey": "Passkey",
  "passkeys": "Passnøkler",
  "passkeysDescription": "Administrer passordene dine for sikker tilgang.",
  "passkeysInstructions": "Få sikker tilgang til kontoen din uten passord.",
  "apiKeys": "API-nøkler",
  "apiKeysDescription": "Administrer API-nøklene dine for sikker tilgang.",
  "apiKeysInstructions": "Generer API-nøkler for å få programmatisk tilgang til kontoen din.",
  "createApiKey": "Opprett API-nøkkel",
  "createApiKeyDescription": "Skriv inn et unikt navn på API-nøkkelen for å skille den fra andre nøkler.",
  "apiKeyNamePlaceholder": "Ny API-nøkkel",
  "apiKeyCreated": "API-nøkkel opprettet",
  "apiKeyCreatedDescription": "Vennligst kopier API-nøkkelen din og oppbevar den på et trygt sted. Av sikkerhetsgrunner kan vi ikke vise den igjen.",
  "neverExpires": "Utløper aldri",
  "expires": "Utløper",
  "noExpiration": "Ingen utløpsdato",
  "create": "Opprett",
  "passwordPlaceholder": "Passord",
  "passwordRequired": "Passord er påkrevd",
  "passwordsDoNotMatch": "Passordene stemmer ikke overens",
  "providers": "Leverandører",
  "providersDescription": "Koble kontoen din til en tredjepartstjeneste.",
  "recoverAccount": "Gjenopprett konto",
  "recoverAccountAction": "Gjenopprett konto",
  "recoverAccountDescription": "Vennligst skriv inn en sikkerhetskopikode for å få tilgang til kontoen din",
  "rememberMe": "Husk meg",
  "resendCode": "Send kode på nytt",
  "resendVerificationEmail": "Send bekreftelses-e-post på nytt",
  "resetPassword": "Tilbakestill passord",
  "resetPasswordAction": "Lagre nytt passord",
  "resetPasswordDescription": "Skriv inn ditt nye passord nedenfor",
  "resetPasswordInvalidToken": "Ugyldig lenke for tilbakestilling av passord",
  "resetPasswordSuccess": "Tilbakestilling av passord vellykket",
  "requestFailed": "Forespørselen mislyktes",
  "revoke": "Tilbakekalle",
  "deleteApiKey": "Slett API-nøkkel",
  "deleteApiKeyConfirmation": "Er du sikker på at du vil slette denne API-nøkkelen?",
  "apiKey": "API-nøkkel",
  "signIn": "Logg inn",
  "signInAction": "Logg inn",
  "signInDescription": "Skriv inn e-postadressen din nedenfor for å logge inn på kontoen din",
  "signInUsernameDescription": "Skriv inn brukernavnet eller e-postadressen din for å logge inn på kontoen din",
  "signInWith": "Logg inn med",
  "signOut": "Logg ut",
  "signUp": "Registrer deg",
  "signUpAction": "Opprett en konto",
  "signUpDescription": "Skriv inn informasjonen din for å opprette en konto",
  "signUpEmail": "Sjekk e-posten din for bekreftelseskoblingen.",
  "sessions": "Sesjoner",
  "sessionsDescription": "Administrer dine aktive økter og tilbakekall tilgang.",
  "setPassword": "Angi passord",
  "setPasswordDescription": "Klikk på knappen nedenfor for å motta en e-post for å sette opp et passord for kontoen din.",
  "settings": "Innstillinger",
  "save": "Spar",
  "security": "Sikkerhet",
  "switchAccount": "Bytt konto",
  "trustDevice": "Stol på denne enheten",
  "twoFactor": "To-faktor",
  "twoFactorAction": "Bekreft kode",
  "twoFactorDescription": "Vennligst skriv inn engangspassordet ditt for å fortsette",
  "twoFactorCardDescription": "Legg til et ekstra sikkerhetslag på kontoen din.",
  "twoFactorDisableInstructions": "Skriv inn passordet ditt for å deaktivere 2FA.",
  "twoFactorEnableInstructions": "Vennligst skriv inn passordet ditt for å aktivere 2FA.",
  "twoFactorEnabled": "To-faktor autentisering er aktivert",
  "twoFactorDisabled": "To-faktor autentisering er deaktivert",
  "twoFactorPrompt": "To-faktor autentisering",
  "twoFactorTotpLabel": "Skann QR-koden med autentiseringsenheten din",
  "sendVerificationCode": "Send bekreftelseskode",
  "unlink": "Fjern koblingen",
  "updatedSuccessfully": "oppdatert vellykket",
  "username": "Brukernavn",
  "usernameDescription": "Skriv inn brukernavnet du vil bruke for å logge på.",
  "usernameInstructions": "Vennligst bruk maksimalt 32 tegn.",
  "usernamePlaceholder": "Brukernavn",
  "signInUsernamePlaceholder": "Brukernavn eller e-post",
  "verifyYourEmail": "Bekreft e-posten din",
  "verifyYourEmailDescription": "Vennligst bekreft e-postadressen din. Sjekk innboksen din for bekreftelses-e-posten. Hvis du ikke har mottatt e-posten, klikker du på knappen nedenfor for å sende den på nytt.",
  "goBack": "Gå tilbake",
  "invalidEmailOrPassword": "Ugyldig e-post eller passord",
  "passwordInvalid": "Ugyldig passord",
  "sessionNotFresh": "Økten din er ikke oppdatert. Vennligst logg inn på nytt.",
  "sessionExpired": "Økten er utløpt",
  "passwordTooShort": "For kort passord",
  "passwordTooLong": "For langt passord",
  "uploadAvatar": "Last opp avatar",
  "privacyPolicy": "Retningslinjer for personvern",
  "termsOfService": "Vilkår for bruk",
  "protectedByRecaptcha": "Dette nettstedet er beskyttet av reCAPTCHA.",
  "byContinuingYouAgree": "Ved å fortsette, samtykker du til",
  "missingCaptchaResponse": "Manglende CAPTCHA-svar"
}
