{
  "email": "E-mail",
  "password": "Hasło",
  "account": "Konto",
  "accounts": "Konta",
  "accountsDescription": "Przełączanie między aktualnie zalogowanymi kontami.",
  "accountsInstructions": "Zaloguj się na dodatkowe konto.",
  "addAccount": "Dodaj konto",
  "addPasskey": "Dodaj klucz dostępu",
  "alreadyHaveAnAccount": "Masz już konto?",
  "avatar": "Awatar",
  "avatarDescription": "Kliknij awatar, aby przesłać niestandardowy awatar ze swoich plików.",
  "avatarInstructions": "Awatar jest opcjonalny, ale zdecydowanie zalecany.",
  "backupCodeRequired": "Wymagany jest kod zapasowy",
  "backupCodes": "Kody kopii zapasowych",
  "backupCodesDescription": "Zapisz te kody zapasowe w bezpiecznym miejscu. Możesz ich użyć, aby uzyskać dostęp do konta, jeśli utracisz metodę uwierzytelniania dwuskładnikowego.",
  "backupCodePlaceholder": "Kod kopii zapasowej",
  "backupCode": "Kod kopii zapasowej",
  "backupCodeAction": "Odzyskaj konto",
  "cancel": "Anuluj",
  "changePassword": "Zmień hasło",
  "changePasswordDescription": "Wprowadź bieżące hasło i nowe hasło.",
  "changePasswordInstructions": "Prosimy o użycie co najmniej 8 znaków.",
  "changePasswordSuccess": "Twoje hasło zostało zmienione.",
  "confirmPassword": "Potwierdź hasło",
  "confirmPasswordPlaceholder": "Potwierdź hasło",
  "confirmPasswordRequired": "Wymagane jest potwierdzenie hasła",
  "continueWithAuthenticator": "Kontynuuj z Authenticator",
  "copiedToClipboard": "Skopiowane do schowka",
  "copyToClipboard": "Kopiuj do schowka",
  "copyAllCodes": "Skopiuj wszystkie kody",
  "continue": "Kontynuuj",
  "currentPassword": "Bieżące hasło",
  "currentPasswordPlaceholder": "Bieżące hasło",
  "currentSession": "Bieżąca sesja",
  "delete": "Usuń",
  "deleteAvatar": "Usuń awatar",
  "deleteAccount": "Usuń konto",
  "deleteAccountDescription": "Trwale usuń swoje konto i całą jego zawartość. Działanie to nie jest odwracalne, więc prosimy o zachowanie ostrożności.",
  "deleteAccountInstructions": "Prosimy o potwierdzenie usunięcia konta. Działanie to nie jest odwracalne, więc prosimy o ostrożne kontynuowanie.",
  "deleteAccountVerify": "Sprawdź pocztę e-mail, aby zweryfikować usunięcie konta.",
  "deleteAccountSuccess": "Twoje konto zostało usunięte.",
  "deleteAccountNotFresh": "Musisz być ostatnio zalogowany, aby usunąć swoje konto.",
  "disable": "Wyłącz",
  "disabledCredentialsDescription": "Wybierz dostawcę, aby zalogować się na swoje konto",
  "dontHaveAnAccount": "Nie masz konta?",
  "done": "Gotowe",
  "emailDescription": "Wprowadź adres e-mail, którego chcesz używać do logowania.",
  "emailInstructions": "Wprowadź prawidłowy adres e-mail.",
  "emailInvalid": "Adres e-mail jest nieprawidłowy",
  "emailIsTheSame": "E-mail jest taki sam",
  "emailPlaceholder": "m@example.com",
  "emailRequired": "Adres e-mail jest wymagany",
  "emailVerifyChange": "Sprawdź pocztę e-mail, aby zweryfikować zmianę.",
  "emailVerification": "Sprawdź swoją wiadomość e-mail, aby uzyskać link weryfikacyjny.",
  "enable": "Włącz",
  "error": "Błąd",
  "isInvalid": "jest nieprawidłowy",
  "isRequired": "jest wymagany",
  "isTheSame": "jest taki sam",
  "forgotAuthenticator": "Zapomniałeś uwierzytelniacza?",
  "forgotPassword": "Nie pamiętam hasła",
  "forgotPasswordAction": "Wyślij link resetowania",
  "forgotPasswordDescription": "Wprowadź swój adres e-mail, aby zresetować hasło",
  "forgotPasswordEmail": "Sprawdź pocztę e-mail, aby uzyskać link do resetowania hasła.",
  "forgotPasswordLink": "Zapomniałeś hasła?",
  "invalidTwoFactorCookie": "Nieprawidłowy dwuczynnikowy plik cookie",
  "link": "Link",
  "magicLink": "Magic Link",
  "magicLinkAction": "Wyślij magiczny link",
  "magicLinkDescription": "Wprowadź swój adres e-mail, aby otrzymać magiczny link",
  "magicLinkEmail": "Sprawdź swój e-mail, aby uzyskać magiczny link",
  "emailOTP": "Kod e-mail",
  "emailOTPSendAction": "Wyślij kod",
  "emailOTPVerifyAction": "Zweryfikuj kod",
  "emailOTPDescription": "Wprowadź swój adres e-mail, aby otrzymać kod",
  "emailOTPVerificationSent": "Sprawdź swoją wiadomość e-mail, aby uzyskać kod weryfikacyjny.",
  "name": "Nazwa",
  "nameDescription": "Wprowadź swoje imię i nazwisko lub nazwę wyświetlaną.",
  "nameInstructions": "Prosimy o użycie maksymalnie 32 znaków.",
  "namePlaceholder": "Nazwa",
  "newPassword": "Nowe hasło",
  "newPasswordPlaceholder": "Nowe hasło",
  "newPasswordRequired": "Wymagane jest nowe hasło",
  "oneTimePassword": "Hasło jednorazowe",
  "orContinueWith": "Lub kontynuować",
  "passkey": "Passkey",
  "passkeys": "Passkeys",
  "passkeysDescription": "Zarządzanie kluczami dostępu w celu zapewnienia bezpiecznego dostępu.",
  "passkeysInstructions": "Bezpieczny dostęp do konta bez hasła.",
  "apiKeys": "Klucze API",
  "apiKeysDescription": "Zarządzaj kluczami API w celu zapewnienia bezpiecznego dostępu.",
  "apiKeysInstructions": "Wygeneruj klucze API, aby uzyskać programowy dostęp do swojego konta.",
  "createApiKey": "Tworzenie klucza API",
  "createApiKeyDescription": "Wprowadź unikalną nazwę klucza API, aby odróżnić go od innych kluczy.",
  "apiKeyNamePlaceholder": "Nowy klucz API",
  "apiKeyCreated": "Utworzony klucz API",
  "apiKeyCreatedDescription": "Prosimy o skopiowanie klucza API i przechowywanie go w bezpiecznym miejscu. Ze względów bezpieczeństwa nie możemy pokazać go ponownie.",
  "neverExpires": "Nigdy nie wygasa",
  "expires": "Wygasa",
  "noExpiration": "Brak wygaśnięcia",
  "create": "Utwórz",
  "passwordPlaceholder": "Hasło",
  "passwordRequired": "Hasło jest wymagane",
  "passwordsDoNotMatch": "Hasła nie są zgodne",
  "providers": "Dostawcy",
  "providersDescription": "Połącz swoje konto z usługą innej firmy.",
  "recoverAccount": "Konto odzyskiwania",
  "recoverAccountAction": "Odzyskaj konto",
  "recoverAccountDescription": "Wprowadź kod zapasowy, aby uzyskać dostęp do konta",
  "rememberMe": "Pamiętaj o mnie",
  "resendCode": "Wyślij ponownie kod",
  "resendVerificationEmail": "Wyślij ponownie e-mail weryfikacyjny",
  "resetPassword": "Resetowanie hasła",
  "resetPasswordAction": "Zapisz nowe hasło",
  "resetPasswordDescription": "Wprowadź nowe hasło poniżej",
  "resetPasswordInvalidToken": "Nieprawidłowy link resetowania hasła",
  "resetPasswordSuccess": "Hasło zostało pomyślnie zresetowane",
  "requestFailed": "Żądanie nie powiodło się",
  "revoke": "Cofnięcie",
  "deleteApiKey": "Usuń klucz API",
  "deleteApiKeyConfirmation": "Czy na pewno chcesz usunąć ten klucz API?",
  "apiKey": "Klucz API",
  "signIn": "Zaloguj się",
  "signInAction": "Logowanie",
  "signInDescription": "Wprowadź swój adres e-mail poniżej, aby zalogować się na swoje konto",
  "signInUsernameDescription": "Wprowadź swoją nazwę użytkownika lub adres e-mail, aby zalogować się na swoje konto.",
  "signInWith": "Zaloguj się za pomocą",
  "signOut": "Wyloguj się",
  "signUp": "Zarejestruj się",
  "signUpAction": "Utwórz konto",
  "signUpDescription": "Wprowadź swoje dane, aby utworzyć konto",
  "signUpEmail": "Sprawdź wiadomość e-mail, aby uzyskać link weryfikacyjny.",
  "sessions": "Sesje",
  "sessionsDescription": "Zarządzanie aktywnymi sesjami i odbieranie dostępu.",
  "setPassword": "Ustaw hasło",
  "setPasswordDescription": "Kliknij poniższy przycisk, aby otrzymać wiadomość e-mail w celu skonfigurowania hasła do konta.",
  "settings": "Ustawienia",
  "save": "Zapisz",
  "security": "Bezpieczeństwo",
  "switchAccount": "Konto Switch",
  "trustDevice": "Zaufaj temu urządzeniu",
  "twoFactor": "Dwuskładnikowy",
  "twoFactorAction": "Zweryfikuj kod",
  "twoFactorDescription": "Wprowadź jednorazowe hasło, aby kontynuować",
  "twoFactorCardDescription": "Dodaj dodatkową warstwę zabezpieczeń do swojego konta.",
  "twoFactorDisableInstructions": "Wprowadź hasło, aby wyłączyć 2FA.",
  "twoFactorEnableInstructions": "Wprowadź hasło, aby włączyć 2FA.",
  "twoFactorEnabled": "Uwierzytelnianie dwuskładnikowe zostało włączone",
  "twoFactorDisabled": "Uwierzytelnianie dwuskładnikowe zostało wyłączone",
  "twoFactorPrompt": "Uwierzytelnianie dwuskładnikowe",
  "twoFactorTotpLabel": "Zeskanuj kod QR za pomocą aplikacji Authenticator",
  "sendVerificationCode": "Wyślij kod weryfikacyjny",
  "unlink": "Unlink",
  "updatedSuccessfully": "pomyślnie zaktualizowany",
  "username": "Nazwa użytkownika",
  "usernameDescription": "Wprowadź nazwę użytkownika, której chcesz używać do logowania.",
  "usernameInstructions": "Prosimy o użycie maksymalnie 32 znaków.",
  "usernamePlaceholder": "Nazwa użytkownika",
  "signInUsernamePlaceholder": "Nazwa użytkownika lub adres e-mail",
  "verifyYourEmail": "Zweryfikuj swój adres e-mail",
  "verifyYourEmailDescription": "Zweryfikuj swój adres e-mail. Sprawdź swoją skrzynkę odbiorczą pod kątem wiadomości weryfikacyjnej. Jeśli nie otrzymałeś wiadomości e-mail, kliknij poniższy przycisk, aby wysłać ją ponownie.",
  "goBack": "Wróć",
  "invalidEmailOrPassword": "Nieprawidłowy adres e-mail lub hasło",
  "passwordInvalid": "Nieprawidłowe hasło",
  "sessionNotFresh": "Twoja sesja nie jest świeża. Zaloguj się ponownie.",
  "sessionExpired": "Sesja wygasła",
  "passwordTooShort": "Zbyt krótkie hasło",
  "passwordTooLong": "Zbyt długie hasło",
  "uploadAvatar": "Prześlij awatar",
  "privacyPolicy": "Polityka prywatności",
  "termsOfService": "Warunki świadczenia usług",
  "protectedByRecaptcha": "Ta strona jest chroniona przez reCAPTCHA.",
  "byContinuingYouAgree": "Kontynuując, użytkownik wyraża zgodę na",
  "missingCaptchaResponse": "Brak odpowiedzi CAPTCHA"
}
